setup.py
chipymap/__init__.py
chipymap.egg-info/PKG-INFO
chipymap.egg-info/SOURCES.txt
chipymap.egg-info/dependency_links.txt
chipymap.egg-info/not-zip-safe
chipymap.egg-info/top_level.txt