Metadata-Version: 1.0
Name: chipymap
Version: 0.1
Summary: geocode Chicago addresses
Home-page:  
Author: Lingwei Cheng
Author-email: UNKNOWN
License: UNKNOWN
Platform: UNKNOWN
